cherry/Master.py
cherry/__init__.py
cherry/api.py
cherry_python-0.3.2.dist-info/LICENSE.txt
cherry_python-0.3.2.dist-info/METADATA
cherry_python-0.3.2.dist-info/WHEEL
cherry_python-0.3.2.dist-info/top_level.txt
cherry_python-0.3.2.dist-info/RECORD
