Metadata-Version: 2.1
Name: cherry-python
Version: 0.3.2
Summary: Cherry Servers API client
Home-page: https://www.cherryservers.com
Download-URL: https://pypi.org/project/cherry-python/#files
Author: Arturas Razinskij
Author-email: arturas.razinskij@cherryservers.com
Maintainer: Cherry Servers Developers
Maintainer-email: support@cherryservers.com
License: LGPL v3
Project-URL: Bug Tracker, https://github.com/cherryservers/cherry-python-api/issues
Project-URL: Source Code, https://github.com/cherryservers/cherry-python-api
Classifier: Development Status :: 5 - Production/Stable
Classifier: Intended Audience :: Developers
Classifier: Intended Audience :: Information Technology
Classifier: License :: OSI Approved :: GNU Lesser General Public License v3 (LGPLv3)
Classifier: Programming Language :: Python :: 2
Classifier: Programming Language :: Python :: 2.7
Classifier: Programming Language :: Python :: 3
Classifier: Programming Language :: Python :: 3.4
Classifier: Programming Language :: Python :: 3.5
Classifier: Programming Language :: Python :: 3.6
License-File: LICENSE.txt
Requires-Dist: requests
